<?xml version="1.0" encoding="windows-1251"?>

<string_table>

	<string id="st_wpn_arisaka">
		<text>Arisaka Type 99</text>
	</string>
	<string id="st_wpn_arisaka_s">
		<text>Type 99</text>
	</string>
	<string id="st_wpn_arisaka_descr">
		<text>Arisaka Type 99 - винтовка с продольно-скользящим затвором, которая была штатной винтовкой пехоты Императорской армии Японии с 1939 года и до конца Второй мировой войны.\n
		Винтовка Type 99, оснащенная ударно-спусковым механизмом и необычным предохранителем, имеет один из самых мощных затворов в истории.\n
		Во время Корейской войны примерно 126 500 коротких и 6 650 длинных винтовок Type 99 были переделаны под стандартный патрон .30-06 Springfield.\n
		Конкретно эта модель была переделана для стрельбы патронами калибра 7,92x57 мм для Национальной революционной армии.\n \n
		%c[ui_gray_2]НАВЕСНОЕ ОБОРУДОВАНИЕ: \n%c[d_purple]• %c[ui_gray_2] прицел ПУ\n \n</text>
	</string>
	
</string_table>
