<?xml version="1.0" encoding="windows-1251"?>
<string_table>
	<string id="st_wpn_colt_saa_j">
		<text>Single Action Army</text>
	</string>
	<string id="st_wpn_colt_saa_j_descr">
		<text>The Colt Single Action Army, often called the "Peacemaker," is one of the most iconic revolvers in American history, renowned for its rugged design and legendary reliability. Traditionally chambered in calibers like .45 Colt, this classic six-shooter is also available in the powerful .357 Magnum, offering a modern twist on a timeless design. With its smooth action, precise balance, and unmistakable style, the Colt Single Action Army remains a favorite among shooters and collectors alike, blending Old West heritage with contemporary performance.\n \n</text>
	</string>
</string_table>